[
    {
        "id": "Tfl760NA63s",
        "title": "[COMEBACK] TXT トゥモローバイトゥギャザー 투모로우바이투게더 - Stick With You [Music Bank] | KBS WORLD TV 260417",
        "channel": "KBS WORLD TV",
        "published_time": "2 日前",
        "url": "https://www.youtube.com/watch?v=Tfl760NA63s",
        "thumbnail": "https://i.ytimg.com/vi/Tfl760NA63s/hqdefault.jpg"
    },
    {
        "id": "jOnLqqDRfY4",
        "title": "TXT (투모로우바이투게더) '하루에 하루만 더 (Stick With You)' Official MV",
        "channel": "HYBE LABELS",
        "published_time": "6 日前",
        "url": "https://www.youtube.com/watch?v=jOnLqqDRfY4",
        "thumbnail": "https://i.ytimg.com/vi/jOnLqqDRfY4/hqdefault.jpg"
    },
    {
        "id": "ni7RpmHjQ1U",
        "title": "So What?- TOMORROW X TOGETHER【カナルビ/歌詞動画/和訳動画】",
        "channel": "すびに",
        "published_time": "5 日前",
        "url": "https://www.youtube.com/watch?v=ni7RpmHjQ1U",
        "thumbnail": "https://i.ytimg.com/vi/ni7RpmHjQ1U/hqdefault.jpg"
    },
    {
        "id": "gSHObxyBGJA",
        "title": "섬세하면서도 절실한 사랑. 투모로우바이투게더 '하루에 하루만 더' 퍼포먼스 필름 최초 공개 (GQ PERFORMANCE With TOMORROW X TOGETHER)",
        "channel": "GQ KOREA",
        "published_time": "4 日前",
        "url": "https://www.youtube.com/watch?v=gSHObxyBGJA",
        "thumbnail": "https://i.ytimg.com/vi/gSHObxyBGJA/hqdefault.jpg"
    },
    {
        "id": "NzOf4Gye0pg",
        "title": "全員ひたすら『かっこいい!』待ちのとぅばちゃんたち《TXT 日本語字幕》",
        "channel": "不思議の国のありす",
        "published_time": "1 日前",
        "url": "https://www.youtube.com/watch?v=NzOf4Gye0pg",
        "thumbnail": "https://i.ytimg.com/vi/NzOf4Gye0pg/hqdefault.jpg"
    },
    {
        "id": "2_ZQpWVMn9c",
        "title": "[Performance37] TXT(투모로우바이투게더) '내일에서 기다릴게 (I'll See You There Tomorrow)' (4K)",
        "channel": "M2",
        "published_time": "2 年前",
        "url": "https://www.youtube.com/watch?v=2_ZQpWVMn9c",
        "thumbnail": "https://i.ytimg.com/vi/2_ZQpWVMn9c/hqdefault.jpg"
    },
    {
        "id": "AnxqqWodceM",
        "title": "TXT (투모로우바이투게더) '하루에 하루만 더 (Stick With You)' Official Teaser",
        "channel": "HYBE LABELS",
        "published_time": "8 日前",
        "url": "https://www.youtube.com/watch?v=AnxqqWodceM",
        "thumbnail": "https://i.ytimg.com/vi/AnxqqWodceM/hqdefault.jpg"
    },
    {
        "id": "FbdFvds7iFs",
        "title": "最強の6人が集まったらこんなんおもろいに決まってる《TXT BIGBANG 日本語字幕》",
        "channel": "不思議の国のありす",
        "published_time": "8 日前",
        "url": "https://www.youtube.com/watch?v=FbdFvds7iFs",
        "thumbnail": "https://i.ytimg.com/vi/FbdFvds7iFs/hqdefault.jpg"
    },
    {
        "id": "J0eLmeiqGQE",
        "title": "[뮤뱅 원테이크 4K] 투모로우바이투게더(TXT) '하루에 하루만 더(Stick With You)' 4K Bonus Ver. @뮤직뱅크 (Music Bank) 260417",
        "channel": "KBS Kpop",
        "published_time": "2 日前",
        "url": "https://www.youtube.com/watch?v=J0eLmeiqGQE",
        "thumbnail": "https://i.ytimg.com/vi/J0eLmeiqGQE/hqdefault.jpg"
    },
    {
        "id": "MwzP97jpvgw",
        "title": "‘Deja Vu+내일에서 기다릴게+Can't Stop' stage @ COUNTDOWN JAPAN 25/26 | TXT(투모로우바이투게더)",
        "channel": "TOMORROW X TOGETHER OFFICIAL",
        "published_time": "2 か月前",
        "url": "https://www.youtube.com/watch?v=MwzP97jpvgw",
        "thumbnail": "https://i.ytimg.com/vi/MwzP97jpvgw/hqdefault.jpg"
    },
    {
        "id": "odd1hKhxQCU",
        "title": "(Interview) Interview with TXT トゥモローバイトゥギャザー 투모로우바이투게더 [Music Bank] | KBS WORLD TV 260417",
        "channel": "KBS WORLD TV",
        "published_time": "2 日前",
        "url": "https://www.youtube.com/watch?v=odd1hKhxQCU",
        "thumbnail": "https://i.ytimg.com/vi/odd1hKhxQCU/hqdefault.jpg"
    },
    {
        "id": "unEThravOoE",
        "title": "TXT (투모로우바이투게더 ) '5時53分の空で見つけた君と僕 [Japanese Ver.]' @ PLAYLIST",
        "channel": "TOMORROW X TOGETHER OFFICIAL",
        "published_time": "5 年前",
        "url": "https://www.youtube.com/watch?v=unEThravOoE",
        "thumbnail": "https://i.ytimg.com/vi/unEThravOoE/hqdefault.jpg"
    },
    {
        "id": "TBS3VbzEQis",
        "title": "‘하루에 하루만 더 (Stick With You)’ stage @ COMEBACK SHOWCASE | TXT (투모로우바이투게더)",
        "channel": "TOMORROW X TOGETHER OFFICIAL",
        "published_time": "4 日前",
        "url": "https://www.youtube.com/watch?v=TBS3VbzEQis",
        "thumbnail": "https://i.ytimg.com/vi/TBS3VbzEQis/hqdefault.jpg"
    },
    {
        "id": "AP2WEsJfPYU",
        "title": "TXT(투모로우바이투게더) ‘Magic’ Special Performance Video",
        "channel": "TOMORROW X TOGETHER OFFICIAL",
        "published_time": "4 年前",
        "url": "https://www.youtube.com/watch?v=AP2WEsJfPYU",
        "thumbnail": "https://i.ytimg.com/vi/AP2WEsJfPYU/hqdefault.jpg"
    },
    {
        "id": "sswmsnPigDc",
        "title": "TXT (투모로우바이투게더) 'Can't Stop' Official MV",
        "channel": "HYBE LABELS",
        "published_time": "5 か月前",
        "url": "https://www.youtube.com/watch?v=sswmsnPigDc",
        "thumbnail": "https://i.ytimg.com/vi/sswmsnPigDc/hqdefault.jpg"
    },
    {
        "id": "JzODRUBBXpc",
        "title": "TXT (투모로우바이투게더) 'LO$ER=LO♡ER' Official MV",
        "channel": "HYBE LABELS",
        "published_time": "4 年前",
        "url": "https://www.youtube.com/watch?v=JzODRUBBXpc",
        "thumbnail": "https://i.ytimg.com/vi/JzODRUBBXpc/hqdefault.jpg"
    },
    {
        "id": "IBv4RCuVnkQ",
        "title": "TOMORROW X TOGETHER '7TH YEAR: 가시덤불에 잠시 바람이 멈췄을 때' COMEBACK SHOWCASE",
        "channel": "HYBE LABELS",
        "published_time": "6 日前 に配信済み",
        "url": "https://www.youtube.com/watch?v=IBv4RCuVnkQ",
        "thumbnail": "https://i.ytimg.com/vi/IBv4RCuVnkQ/hqdefault.jpg"
    },
    {
        "id": "EUERJYKCzWU",
        "title": "[2026 DREAM WEEK] DAY & NIGHT Medley Live | TXT (투모로우바이투게더)️",
        "channel": "TOMORROW X TOGETHER OFFICIAL",
        "published_time": "1 か月前",
        "url": "https://www.youtube.com/watch?v=EUERJYKCzWU",
        "thumbnail": "https://i.ytimg.com/vi/EUERJYKCzWU/hqdefault.jpg"
    },
    {
        "id": "wgJEOB_CsGc",
        "title": "TXT(투모로우바이투게더) 'Ito'  @ CDTV LIVE! LIVE! Christmas Special",
        "channel": "TOMORROW X TOGETHER OFFICIAL",
        "published_time": "4 年前",
        "url": "https://www.youtube.com/watch?v=wgJEOB_CsGc",
        "thumbnail": "https://i.ytimg.com/vi/wgJEOB_CsGc/hqdefault.jpg"
    }
]