[
    {
        "id": "2_ZQpWVMn9c",
        "title": "[Performance37] TXT(투모로우바이투게더) '내일에서 기다릴게 (I'll See You There Tomorrow)' (4K)",
        "channel": "M2",
        "published_time": "2y ago",
        "url": "https://www.youtube.com/watch?v=2_ZQpWVMn9c",
        "thumbnail": "https://i.ytimg.com/vi/2_ZQpWVMn9c/hqdefault.jpg"
    },
    {
        "id": "Z6o28Y0rPGk",
        "title": "TOMORROW X TOGETHER (투모로우바이투게더) - Upside Down Kiss | Show! MusicCore | MBC250726방송",
        "channel": "MBCkpop",
        "published_time": "11mo ago",
        "url": "https://www.youtube.com/watch?v=Z6o28Y0rPGk",
        "thumbnail": "https://i.ytimg.com/vi/Z6o28Y0rPGk/hqdefault.jpg"
    },
    {
        "id": "SMN0QRl-Pz0",
        "title": "무조건적인 지지와 사랑 | Listening Session | 연준 (YEONJUN)",
        "channel": "TOMORROW X TOGETHER OFFICIAL",
        "published_time": "11h ago",
        "url": "https://www.youtube.com/watch?v=SMN0QRl-Pz0",
        "thumbnail": "https://i.ytimg.com/vi/SMN0QRl-Pz0/hqdefault.jpg"
    },
    {
        "id": "jOnLqqDRfY4",
        "title": "TXT (투모로우바이투게더) '하루에 하루만 더 (Stick With You)' Official MV",
        "channel": "HYBE LABELS",
        "published_time": "2mo ago",
        "url": "https://www.youtube.com/watch?v=jOnLqqDRfY4",
        "thumbnail": "https://i.ytimg.com/vi/jOnLqqDRfY4/hqdefault.jpg"
    },
    {
        "id": "-rfwgn2XQMo",
        "title": "[KOR] TXT Tomorrow X Together | FULL ALBUM TOP HITS PLAYLIST POPULER CONCERT 2025",
        "channel": "Recommendation Playlist",
        "published_time": "1y ago",
        "url": "https://www.youtube.com/watch?v=-rfwgn2XQMo",
        "thumbnail": "https://i.ytimg.com/vi/-rfwgn2XQMo/hqdefault.jpg"
    },
    {
        "id": "9-zsP0yj_1Q",
        "title": "[단독샷캠4K] 투모로우바이투게더 'Good Boy Gone Bad' 단독샷 별도녹화│TOMORROW X TOGETHER ONE TAKE STAGE│@SBSInkigayo22515",
        "channel": "SBSKPOP X INKIGAYO",
        "published_time": "4y ago",
        "url": "https://www.youtube.com/watch?v=9-zsP0yj_1Q",
        "thumbnail": "https://i.ytimg.com/vi/9-zsP0yj_1Q/hqdefault.jpg"
    },
    {
        "id": "C0EYKxF1oTI",
        "title": "TXT (투모로우바이투게더), Jonas Brothers 'Do It Like That' Official MV",
        "channel": "HYBE LABELS",
        "published_time": "3y ago",
        "url": "https://www.youtube.com/watch?v=C0EYKxF1oTI",
        "thumbnail": "https://i.ytimg.com/vi/C0EYKxF1oTI/hqdefault.jpg"
    },
    {
        "id": "ihvuwqlGHXs",
        "title": "YEONJUN (연준) 'Ice Cream' Official MV",
        "channel": "HYBE LABELS and TOMORROW X TOGETHER OFFICIAL",
        "published_time": "2d ago",
        "url": "https://www.youtube.com/watch?v=ihvuwqlGHXs",
        "thumbnail": "https://i.ytimg.com/vi/ihvuwqlGHXs/hqdefault.jpg"
    },
    {
        "id": "8aRTMQvbODs",
        "title": "TXT (투모로우바이투게더) 'Love Language' Official MV",
        "channel": "HYBE LABELS",
        "published_time": "1y ago",
        "url": "https://www.youtube.com/watch?v=8aRTMQvbODs",
        "thumbnail": "https://i.ytimg.com/vi/8aRTMQvbODs/hqdefault.jpg"
    },
    {
        "id": "jDCUXToLZsg",
        "title": "TOMORROW X TOGETHER - Upside Down Kiss | Show! MusicCore | aired on MBC250726 #TXT",
        "channel": "MBC WORLD",
        "published_time": "11mo ago",
        "url": "https://www.youtube.com/watch?v=jDCUXToLZsg",
        "thumbnail": "https://i.ytimg.com/vi/jDCUXToLZsg/hqdefault.jpg"
    },
    {
        "id": "ERtruwl7NMU",
        "title": "[뮤뱅 원테이크 4K] 투모로우바이투게더(TXT) 'Love Language' 4K Bonus Ver. @뮤직뱅크(Music Bank) 250502",
        "channel": "KBS Kpop",
        "published_time": "1y ago",
        "url": "https://www.youtube.com/watch?v=ERtruwl7NMU",
        "thumbnail": "https://i.ytimg.com/vi/ERtruwl7NMU/hqdefault.jpg"
    },
    {
        "id": "P9tKTxbgdkk",
        "title": "TXT (투모로우바이투게더) 'Sugar Rush Ride' Official MV",
        "channel": "HYBE LABELS",
        "published_time": "3y ago",
        "url": "https://www.youtube.com/watch?v=P9tKTxbgdkk",
        "thumbnail": "https://i.ytimg.com/vi/P9tKTxbgdkk/hqdefault.jpg"
    },
    {
        "id": "EzJ7wCz_iK0",
        "title": "[최초공개] TXT (투모로우바이투게더) - No Rules (4K) | TXT COMEBACKSHOW 'FREEZE' | Mnet 210531 방송",
        "channel": "M2",
        "published_time": "5y ago",
        "url": "https://www.youtube.com/watch?v=EzJ7wCz_iK0",
        "thumbnail": "https://i.ytimg.com/vi/EzJ7wCz_iK0/hqdefault.jpg"
    },
    {
        "id": "Vd9QkWsd5p4",
        "title": "TXT (투모로우바이투게더) '5시 53분의 하늘에서 발견한 너와 나' Official MV",
        "channel": "HYBE LABELS",
        "published_time": "5y ago",
        "url": "https://www.youtube.com/watch?v=Vd9QkWsd5p4",
        "thumbnail": "https://i.ytimg.com/vi/Vd9QkWsd5p4/hqdefault.jpg"
    },
    {
        "id": "_A1hx2FMv6I",
        "title": "없던 서사도 생겨나는 음색 🍋 ‘Lemon - 범규, 태현, 휴닝카이 (원곡: 米津玄師(요네즈 켄시)) [가사해석/Lyrics]",
        "channel": "최강정",
        "published_time": "7d ago",
        "url": "https://www.youtube.com/watch?v=_A1hx2FMv6I",
        "thumbnail": "https://i.ytimg.com/vi/_A1hx2FMv6I/hqdefault.jpg"
    },
    {
        "id": "oxGHJSbOY3k",
        "title": "TXT(투모로우바이투게더) 'Over The Moon' (4K) | STUDIO CHOOM ORIGINAL",
        "channel": "STUDIO CHOOM [스튜디오 춤]",
        "published_time": "1y ago",
        "url": "https://www.youtube.com/watch?v=oxGHJSbOY3k",
        "thumbnail": "https://i.ytimg.com/vi/oxGHJSbOY3k/hqdefault.jpg"
    },
    {
        "id": "EUERJYKCzWU",
        "title": "[2026 DREAM WEEK] DAY & NIGHT Medley Live | TXT (투모로우바이투게더)️",
        "channel": "TOMORROW X TOGETHER OFFICIAL",
        "published_time": "4mo ago",
        "url": "https://www.youtube.com/watch?v=EUERJYKCzWU",
        "thumbnail": "https://i.ytimg.com/vi/EUERJYKCzWU/hqdefault.jpg"
    },
    {
        "id": "JzODRUBBXpc",
        "title": "TXT (투모로우바이투게더) 'LO$ER=LO♡ER' Official MV",
        "channel": "HYBE LABELS",
        "published_time": "4y ago",
        "url": "https://www.youtube.com/watch?v=JzODRUBBXpc",
        "thumbnail": "https://i.ytimg.com/vi/JzODRUBBXpc/hqdefault.jpg"
    },
    {
        "id": "sswmsnPigDc",
        "title": "TXT (투모로우바이투게더) 'Can't Stop' Official MV",
        "channel": "HYBE LABELS",
        "published_time": "8mo ago",
        "url": "https://www.youtube.com/watch?v=sswmsnPigDc",
        "thumbnail": "https://i.ytimg.com/vi/sswmsnPigDc/hqdefault.jpg"
    }
]